formy/__init__.py
formy/fields.py
formy/form.py
formy/templates/formy/fields/base.html
formy/templates/formy/fields/ckeditor.html
formy/templates/formy/fields/select-multiple.html
formy/templates/formy/fields/select.html
formy/templates/formy/fields/textarea.html
formy/templates/formy/form/table.html
formy/templates/formy/form/ul.html
formy/tests/__init__.py
formy/tests/fields.py
formy/tests/form.py
formy/utils.py
formy-1.3.1.dist-info/LICENSE
formy-1.3.1.dist-info/WHEEL
formy-1.3.1.dist-info/METADATA
formy-1.3.1.dist-info/RECORD
